MANIFEST.in
README.md
README.rst
setup.cfg
setup.py
share/applications/whiterenamer.desktop
share/menu/whiterenamer
share/pixmaps/whiterenamer.png
share/pixmaps/whiterenamer.xpm
whiterenamer/__init__.py
whiterenamer/run.py
whiterenamer.egg-info/PKG-INFO
whiterenamer.egg-info/SOURCES.txt
whiterenamer.egg-info/dependency_links.txt
whiterenamer.egg-info/entry_points.txt
whiterenamer.egg-info/not-zip-safe
whiterenamer.egg-info/requires.txt
whiterenamer.egg-info/top_level.txt
whiterenamer/doc/Documentation.pdf
whiterenamer/model/__init__.py
whiterenamer/model/action_manager.py
whiterenamer/model/file_system.py
whiterenamer/ui/__init__.py
whiterenamer/ui/action_button_group.py
whiterenamer/ui/file_system_view.py
whiterenamer/ui/main_widget.py
whiterenamer/ui/main_window.py
whiterenamer/ui/resource_rc.py