Metadata-Version: 1.0
Name: whiterenamer
Version: 1.0.0
Summary: User friendly batch renamer
Home-page: https://github.com/pierrecnalb/White-Renamer
Author: Pierre Blanc
Author-email: pierrecnalb@mailbox.org
License: GNU Public General License
Keywords: batch renamer gui simple exif photo music metadata
Platform: UNKNOWN
